README.txt
setup.py
docs/HISTORY.txt
inquant/__init__.py
inquant/msp2plone/__init__.py
msp2plone.egg-info/PKG-INFO
msp2plone.egg-info/SOURCES.txt
msp2plone.egg-info/dependency_links.txt
msp2plone.egg-info/entry_points.txt
msp2plone.egg-info/namespace_packages.txt
msp2plone.egg-info/not-zip-safe
msp2plone.egg-info/requires.txt
msp2plone.egg-info/top_level.txt