Metadata-Version: 1.0
Name: msp2plone
Version: 0.9b
Summary: An M$ Project XML to Plone 'eXtreme Management' importer.
Home-page: https://msp2plone.googlecode.com/svn/tags/0.9b
Author: Stefan Eletzhofer
Author-email: stefan.eletzhofer@inquant.de
License: GPL
Platform: UNKNOWN
Classifier: Programming Language :: Python
